smartredis-0.6.1.dist-info/LICENSE.md
smartredis-0.6.1.dist-info/METADATA
smartredis-0.6.1.dist-info/RECORD
smartredis-0.6.1.dist-info/WHEEL
smartredis-0.6.1.dist-info/top_level.txt
smartredis/error.py
smartredis/client.py
smartredis/dataset_utils.py
smartredis/dataset.py
smartredis/logger.py
smartredis/logcontext.py
smartredis/smartredisPy.cpython-39-x86_64-linux-gnu.so
smartredis/configoptions.py
smartredis/util.py
smartredis/srobject.py
smartredis/__init__.py
smartredis/py.typed
