Metadata-Version: 2.1
Name: smartredis
Version: 0.6.1
Summary: RedisAI clients for SmartSim
Home-page: https://github.com/CrayLabs/SmartRedis
Author: CrayLabs, a Hewlett Packard Enterprise OSS Organization
Author-email: craylabs@hpe.com
License: BSD 2-Clause License
Project-URL: Source, https://github.com/CrayLabs/SmartRedis
Project-URL: Documentation, https://www.craylabs.org
Keywords: redis,clients,hpc,ai,deep learning
Platform: UNKNOWN
Classifier: Programming Language :: Python :: 3.9
Classifier: Programming Language :: Python :: 3.10
Classifier: Programming Language :: Python :: 3.11
Classifier: License :: OSI Approved :: BSD License
Classifier: Intended Audience :: Science/Research
Classifier: Topic :: Scientific/Engineering
Requires-Python: <3.12,>=3.9
Provides-Extra: dev
Provides-Extra: doc
Provides-Extra: xarray
License-File: LICENSE.md
